taizun/__init__.py
taizun/nlp.py
taizun/utils.py
taizun/vision.py
taizun-0.97.dist-info/LICENSE.txt
taizun-0.97.dist-info/METADATA
taizun-0.97.dist-info/WHEEL
taizun-0.97.dist-info/top_level.txt
taizun-0.97.dist-info/RECORD
