Metadata-Version: 2.1
Name: taizun
Version: 0.97
Summary: A Python library for simplifying tasks and enhancing generative AI workflows.
Home-page: https://github.com/t4zn/taizun
Author: Taizun
Author-email: taizun8@gmail.com
Classifier: Programming Language :: Python :: 3
Classifier: License :: OSI Approved :: MIT License
Classifier: Operating System :: OS Independent
Requires-Python: >=3.6
License-File: LICENSE.txt
Requires-Dist: transformers
Requires-Dist: torch
Requires-Dist: Pillow
